hw_cli/__init__.py
hw_cli/__main__.py
hw_cli/commands/__init__.py
hw_cli/commands/cache.py
hw_cli/commands/config_cmd.py
hw_cli/commands/devices.py
hw_cli/commands/enrollment.py
hw_cli/commands/simulate.py
hw_cli/core/__init__.py
hw_cli/core/config.py
hw_cli/core/device_manager.py
hw_cli/core/identity/azure_dps_provisioner.py
hw_cli/core/identity/provisioning_cache.py
hw_cli/core/models/models.py
hw_cli/core/models/weather_pb2.py
hw_cli/core/publisher/azure_publisher.py
hw_cli/core/publisher/data_publisher.py
hw_cli/core/publisher/fake_data_publisher.py
hw_cli/core/simulation/data_generator.py
hw_cli/core/simulation/sim_data_gen.py
hw_cli/core/storage.py
hw_cli/utils/console.py
hw_cli/utils/telemetry_format.py
heavyweather_cli-0.2.0.dist-info/METADATA
heavyweather_cli-0.2.0.dist-info/WHEEL
heavyweather_cli-0.2.0.dist-info/entry_points.txt
heavyweather_cli-0.2.0.dist-info/RECORD
