Metadata-Version: 2.4
Name: heavyweather-cli
Version: 0.2.0
Summary: Heavy Weather CLI
Requires-Python: >=3.9,<4.0
Classifier: Programming Language :: Python :: 3
Classifier: Programming Language :: Python :: 3.9
Classifier: Programming Language :: Python :: 3.10
Classifier: Programming Language :: Python :: 3.11
Classifier: Programming Language :: Python :: 3.12
Classifier: Programming Language :: Python :: 3.13
Classifier: Programming Language :: Python :: 3.14
Requires-Dist: azure-iot-device (>=2.14.0,<3.0.0)
Requires-Dist: protobuf (>=6.32.1,<7.0.0)
Requires-Dist: pyyaml (>=6.0.2,<7.0.0)
Requires-Dist: typer[rich] (>=0.17.4,<0.18.0)
